[
  {
    "discount": 30,
    "link": "https://www.auchan.fr/lego-ideas-21352-la-magie-de-disney/pr-C1804269",
    "price": 69.99,
    "title": "Jouet Lego Ideas 21352 - La Magie de Disney (Via 30€ sur la carte fidélité)",
    "imgUrl": "https://static-pepper.dealabs.com/threads/raw/rSfEC/2962023_1/re/300x300/qt/60/2962023_1.jpg",
    "legoID": "21352",
    "retail": 99.99,
    "commentCount": 0,
    "temperature": 12.9,
    "published": 1735317933,
    "linkDealLabs": "https://www.dealabs.com/share-deal/2962023"
  },
  {
    "discount": 22.51,
    "link": "https://www.cdiscount.com/juniors/lego/nouveautes-lego-2025/l-1202833-2.html",
    "price": 30.99,
    "title": "Sélection de LEGO en Précommande en Promotion - Ex : LEGO Technic - Le sous-marin de recherche en haute mer (42201)",
    "imgUrl": "https://static-pepper.dealabs.com/threads/raw/lMg8W/2961916_1/re/300x300/qt/60/2961916_1.jpg",
    "legoID": "42201",
    "retail": 39.99,
    "commentCount": 0,
    "temperature": 11.45,
    "published": 1735305333,
    "linkDealLabs": "https://www.dealabs.com/share-deal/2961916"
  },
  {
    "discount": 20,
    "link": "https://www.cdiscount.com/juniors/maquette-modelisme/lego-city-60445-camion-de-f1-avec-voitures-de-f1-r/f-12084-lego60445.html",
    "price": 79.99,
    "title": "[Précommande] LEGO City 60445 Camion de F1 avec voitures de F1 RB20 et AMR24",
    "imgUrl": "https://static-pepper.dealabs.com/threads/raw/wb9WA/2961826_1/re/300x300/qt/60/2961826_1.jpg",
    "legoID": "60445",
    "retail": 99.99,
    "commentCount": 4,
    "temperature": 31,
    "published": 1735297736,
    "linkDealLabs": "https://www.dealabs.com/share-deal/2961826"
  },
  {
    "discount": 26.68,
    "link": "https://www.cdiscount.com/juniors/maquette-modelisme/lego-40678-le-calendrier-des-fetes-idee-cadeau-e/f-12084-lego40678.html",
    "price": 21.99,
    "title": "[Précommande] LEGO 40678 Le calendrier des fêtes pour le Nouvel An lunaire",
    "imgUrl": "https://static-pepper.dealabs.com/threads/raw/9eQLj/2961724_1/re/300x300/qt/60/2961724_1.jpg",
    "legoID": "40678",
    "retail": 29.99,
    "commentCount": 5,
    "temperature": 62.28,
    "published": 1735289802,
    "linkDealLabs": "https://www.dealabs.com/share-deal/2961724"
  },
  {
    "discount": 23.34,
    "link": "https://www.cdiscount.com/juniors/maquette-modelisme/lego-dc-batman-76303-la-batmobile-tumbler-de-batma/f-12084-lego76303.html",
    "price": 45.99,
    "title": "LEGO DC Batman 76303 La Batmobile Tumbler de Batman contre Double-Face et Le Joker",
    "imgUrl": "https://static-pepper.dealabs.com/threads/raw/BL5xP/2961681_1/re/300x300/qt/60/2961681_1.jpg",
    "legoID": "76303",
    "retail": 59.99,
    "commentCount": 10,
    "temperature": 132.9,
    "published": 1735286091,
    "linkDealLabs": "https://www.dealabs.com/share-deal/2961681"
  },
  {
    "discount": 13.36,
    "link": "https://www.amazon.fr/dp/B0CFVZ74KT?smid=A1X6FK5RDHNB96",
    "price": 155.9,
    "title": "Jeu de construction Lego Technic Mercedes-AMG F1 W14 E Performance 42171",
    "imgUrl": "https://static-pepper.dealabs.com/threads/raw/7rx8Y/2961613_1/re/300x300/qt/60/2961613_1.jpg",
    "legoID": "42171",
    "retail": 179.93,
    "commentCount": 6,
    "temperature": 35.66,
    "published": 1735261659,
    "linkDealLabs": "https://www.dealabs.com/share-deal/2961613"
  },
  {
    "discount": 30,
    "link": "",
    "price": 102.83,
    "title": "Lego (42156) - Peugeot 9X8 24H Le Mans Hybrid Hypercar (Via 44.07€ sur la Carte de Fidélité) - Mondeville 2 (14)",
    "imgUrl": "https://static-pepper.dealabs.com/threads/raw/3UBfl/2961425_1/re/300x300/qt/60/2961425_1.jpg",
    "legoID": "42156",
    "retail": 146.9,
    "commentCount": 7,
    "temperature": 85.6,
    "published": 1735236287,
    "linkDealLabs": "https://www.dealabs.com/share-deal/2961425"
  },
  {
    "discount": 70,
    "link": "https://auchan.fr/lego-dots-41808-ensemble-d-rsquo-accessoires-poudlard-jouet-creation-de-bijoux-sur-harry-potter-avec-bracelet-2-etiquettes-et-plaque/pr-C1633765",
    "price": 3.87,
    "title": "LEGO Dots Harry Potter (41808) - Ensemble d’accessoires Poudlard (Via 9.03€ sur la Carte de Fidélité)",
    "imgUrl": "https://static-pepper.dealabs.com/threads/raw/gaSQ6/2961385_1/re/300x300/qt/60/2961385_1.jpg",
    "legoID": "41808",
    "retail": 12.9,
    "commentCount": 1,
    "temperature": 94.37,
    "published": 1735231421,
    "linkDealLabs": "https://www.dealabs.com/share-deal/2961385"
  },
  {
    "discount": 0,
    "link": "https://www.lego.com/fr-fr/page/lego-offers-promotions",
    "price": 0,
    "title": "Lego 40689 Le Feu d’Artifice offert, dès 85€ d'achat (hors précommandes)",
    "imgUrl": "https://static-pepper.dealabs.com/threads/raw/LjXOx/2961340_1/re/300x300/qt/60/2961340_1.jpg",
    "legoID": "40689",
    "retail": 0,
    "commentCount": 0,
    "temperature": 13.56,
    "published": 1735227877,
    "linkDealLabs": "https://www.dealabs.com/share-deal/2961340"
  },
  {
    "discount": 15.84,
    "link": "https://www.alternate.fr/Lego/Technic-Mercedes-Benz-G-500-PROFESSIONAL-Line-Jouets-de-construction/html/product/100044211",
    "price": 159.9,
    "title": "Jouet Lego Technic - Mercedes-Benz G 500 Professional Line 42177",
    "imgUrl": "https://static-pepper.dealabs.com/threads/raw/ePHBs/2961333_1/re/300x300/qt/60/2961333_1.jpg",
    "legoID": "42177",
    "retail": 190,
    "commentCount": 1,
    "temperature": 49.74,
    "published": 1735227191,
    "linkDealLabs": "https://www.dealabs.com/share-deal/2961333"
  },
  {
    "discount": 30,
    "link": "https://www.dreamland.be/e/fr/dl/lego-ideas--la-maison-en-a-21338-146152",
    "price": 125.3,
    "title": "Sélection de sets Lego en promotion EX : Le chalet en A 21338 (Frontaliers Belgique)",
    "imgUrl": "https://static-pepper.dealabs.com/threads/raw/PUcxj/2961264_1/re/300x300/qt/60/2961264_1.jpg",
    "legoID": "21338",
    "retail": 179,
    "commentCount": 7,
    "temperature": 260.33,
    "published": 1735219362,
    "linkDealLabs": "https://www.dealabs.com/share-deal/2961264"
  },
  {
    "discount": 0,
    "link": "https://www.carrefour.fr/p/lego-minecraft-la-maison-de-la-plage-de-la-tortue-21254-lego-5702017583303",
    "price": 18.9,
    "title": "Lego Minecraft 21254 La Maison de la Plage de la Tortue (Sélection de magasins)",
    "imgUrl": "https://static-pepper.dealabs.com/threads/raw/zdCoT/2961256_1/re/300x300/qt/60/2961256_1.jpg",
    "legoID": "21254",
    "retail": 0,
    "commentCount": 0,
    "temperature": 26.33,
    "published": 1735218938,
    "linkDealLabs": "https://www.dealabs.com/share-deal/2961256"
  },
  {
    "discount": 12.36,
    "link": "https://www.auchan.fr/lego-star-wars-75380-la-menace-fantome-diorama-de-la-course-de-podracers-de-mos-espa-maquette-a-construire-set-de-collection-a-offrir-aux-adultes-inclut-le-podracer-d-anakin-skywalker/pr-C1791755",
    "price": 48.99,
    "title": "Lego Star Wars 75380 La Menace Fantôme Diorama de la Course de Podracers de Mos Espa (Via 21€ sur la Carte de Fidélité)",
    "imgUrl": "https://static-pepper.dealabs.com/threads/raw/MfxL3/2961255_1/re/300x300/qt/60/2961255_1.jpg",
    "legoID": "75380",
    "retail": 55.9,
    "commentCount": 1,
    "temperature": 40.33,
    "published": 1735218897,
    "linkDealLabs": "https://www.dealabs.com/share-deal/2961255"
  },
  {
    "discount": 50.04,
    "link": "https://www.auchan.fr/lego-40640-le-casse-noisettes-decoration-de-noel/pr-C1814162",
    "price": 6.49,
    "title": "Lego 40640 Le Casse-Noisettes (Via 6,50€ sur la Carte de Fidélité)",
    "imgUrl": "https://static-pepper.dealabs.com/threads/raw/a9zvQ/2961253_1/re/300x300/qt/60/2961253_1.jpg",
    "legoID": "40640",
    "retail": 12.99,
    "commentCount": 4,
    "temperature": 265.16,
    "published": 1735218686,
    "linkDealLabs": "https://www.dealabs.com/share-deal/2961253"
  },
  {
    "discount": 50.01,
    "link": "https://www.carrefour.fr/p/lego-disney-le-train-en-fete-disney-43212-lego-5702017424798",
    "price": 18.49,
    "title": "Lego Disney 43212 Le Train en Fête Disney (Via 18,50€ sur la Carte de Fidélité) - (Sélection de magasins)",
    "imgUrl": "https://static-pepper.dealabs.com/threads/raw/vmeoH/2961171_1/re/300x300/qt/60/2961171_1.jpg",
    "legoID": "43212",
    "retail": 36.99,
    "commentCount": 16,
    "temperature": 243.65,
    "published": 1735211319,
    "linkDealLabs": "https://www.dealabs.com/share-deal/2961171"
  },
  {
    "discount": 21.09,
    "link": "https://www.amazon.fr/dp/B0CFVN4XVL?smid=A1X6FK5RDHNB96",
    "price": 6.96,
    "title": "Lego Technic 42163 Le Bulldozer",
    "imgUrl": "https://static-pepper.dealabs.com/threads/raw/n7Gf7/2961018_1/re/300x300/qt/60/2961018_1.jpg",
    "legoID": "42163",
    "retail": 8.82,
    "commentCount": 0,
    "temperature": 80.88,
    "published": 1735201414,
    "linkDealLabs": "https://www.dealabs.com/share-deal/2961018"
  },
  {
    "discount": 50,
    "link": "https://www.auchan.fr/lego-disney-classic-43243-simba-le-bebe-du-roi-lion-jouet-de-construction-pour-enfants-figurine-a-construire-jouet-d-activite-et-de-developpement/pr-C1793110",
    "price": 9.45,
    "title": "Lego Disney Classic 43243 Simba, le Bébé du Roi Lion (Via 9,45€ sur la Carte de Fidélité)",
    "imgUrl": "https://static-pepper.dealabs.com/threads/raw/yHuom/2960995_1/re/300x300/qt/60/2960995_1.jpg",
    "legoID": "43243",
    "retail": 18.9,
    "commentCount": 3,
    "temperature": 424.57,
    "published": 1735200913,
    "linkDealLabs": "https://www.dealabs.com/share-deal/2960995"
  },
  {
    "discount": 30,
    "link": "https://www.auchan.fr/jouets-jeux-video-loisirs/jeux-jouets/lego-playmobil-construction/lego/lego-star-wars/ca-6860523",
    "price": 34.93,
    "title": "30% cagnottés sur une sélection de Lego Star Wars - Ex: Lego Star Wars 75377 La Main Invisible (Via 14,97€ sur la Carte de Fidélité)",
    "imgUrl": "https://static-pepper.dealabs.com/threads/raw/pLASi/2961011_1/re/300x300/qt/60/2961011_1.jpg",
    "legoID": "75377",
    "retail": 49.9,
    "commentCount": 9,
    "temperature": 400.37,
    "published": 1735200823,
    "linkDealLabs": "https://www.dealabs.com/share-deal/2961011"
  },
  {
    "discount": 27.27,
    "link": "https://www.auchan.fr/lego-star-wars-75393-tie-fighter-et-x-wing-a-combiner/pr-C1802535",
    "price": 55.93,
    "title": "Lego Stars Wars 75393 Tie Fighter et X-Wing à combiner (Via 23,97€ sur la Carte de Fidélité)",
    "imgUrl": "https://static-pepper.dealabs.com/threads/raw/jHrgd/2960993_1/re/300x300/qt/60/2960993_1.jpg",
    "legoID": "75393",
    "retail": 76.9,
    "commentCount": 1,
    "temperature": 59.02,
    "published": 1735199316,
    "linkDealLabs": "https://www.dealabs.com/share-deal/2960993"
  },
  {
    "discount": 50,
    "link": "https://www.auchan.fr/lego-speed-champions-76925-aston-martin-safety-car-amr23-set-de-construction-inclut-deux-minifigurines-et-2-repliques-de-vehicules/pr-C1793274",
    "price": 24.45,
    "title": "Lego Speed Champions 76925 - Aston Martin Safety Car & AMR23 (Via 24,45 sur la Carte de Fidélité)",
    "imgUrl": "https://static-pepper.dealabs.com/threads/raw/Vx2zc/2960981_1/re/300x300/qt/60/2960981_1.jpg",
    "legoID": "76925",
    "retail": 48.9,
    "commentCount": 21,
    "temperature": 705.49,
    "published": 1735197377,
    "linkDealLabs": "https://www.dealabs.com/share-deal/2960981"
  },
  {
    "discount": 40.01,
    "link": "https://www.joueclub.fr/jeux-de-constructions-maquettes/lego-friends-41734-le-bateau-de-sauvetage-en-mer-5702017415192.html",
    "price": 47.99,
    "title": "Jeu de construction Lego Friends : Bateau de sauvetage en mer (41734)",
    "imgUrl": "https://static-pepper.dealabs.com/threads/raw/7Lt5k/2960897_1/re/300x300/qt/60/2960897_1.jpg",
    "legoID": "41734",
    "retail": 79.99,
    "commentCount": 0,
    "temperature": 30.86,
    "published": 1735168426,
    "linkDealLabs": "https://www.dealabs.com/share-deal/2960897"
  },
  {
    "discount": 18.03,
    "link": "https://www.alternate.fr/LEGO/Creator-Expert-ECTO-1-SOS-Fant%C3%B4mes-Jouets-de-construction/html/product/1702615",
    "price": 195.9,
    "title": "Jeu de construction Lego Creator Expert 10274 - ECTO-1 SOS Fantômes",
    "imgUrl": "https://static-pepper.dealabs.com/threads/raw/UjH8u/2960858_1/re/300x300/qt/60/2960858_1.jpg",
    "legoID": "10274",
    "retail": 239,
    "commentCount": 8,
    "temperature": -60.82,
    "published": 1735162430,
    "linkDealLabs": "https://www.dealabs.com/share-deal/2960858"
  },
  {
    "discount": 10,
    "link": "https://www.king-jouet.com/jeu-jouet/jeux-constructions/lego-planchettes/ref-951598-10318-lego-icons-le-concorde.htm",
    "price": 179.99,
    "title": "Jeu de construction Lego Icons (10318) - Le Concorde",
    "imgUrl": "https://static-pepper.dealabs.com/threads/raw/G0j9e/2960733_1/re/300x300/qt/60/2960733_1.jpg",
    "legoID": "10318",
    "retail": 200,
    "commentCount": 4,
    "temperature": 14.28,
    "published": 1735147312,
    "linkDealLabs": "https://www.dealabs.com/share-deal/2960733"
  },
  {
    "discount": 0,
    "link": "https://www.king-jouet.com/jeu-jouet/jeux-constructions/lego-planchettes/ref-951690-42633-lego-friends-le-food-truck-de-hot-dogs.htm",
    "price": 11.99,
    "title": "jeu de construction LEGO Friends 42633 - Le Food-Truck de Hot-Dogs kike",
    "imgUrl": "https://static-pepper.dealabs.com/threads/raw/ix16y/2960647_1/re/300x300/qt/60/2960647_1.jpg",
    "legoID": "42633",
    "retail": 0,
    "commentCount": 1,
    "temperature": 33.26,
    "published": 1735134427,
    "linkDealLabs": "https://www.dealabs.com/share-deal/2960647"
  },
  {
    "discount": 23.34,
    "link": "https://www.cdiscount.com/juniors/maquette-modelisme/lego-creator-31161-3-en-1-le-dragon-medieval-jeu/f-12084-lego31161.html",
    "price": 45.99,
    "title": "Sélection de LEGO en réduction en précommande, EX : LEGO Creator 31161 3-en-1 Le dragon médiéval",
    "imgUrl": "https://static-pepper.dealabs.com/threads/raw/5DBLa/2960590_1/re/300x300/qt/60/2960590_1.jpg",
    "legoID": "31161",
    "retail": 59.99,
    "commentCount": 5,
    "temperature": 355.4,
    "published": 1735126384,
    "linkDealLabs": "https://www.dealabs.com/share-deal/2960590"
  },
  {
    "discount": 30.19,
    "link": "https://www.carrefour.fr/p/lego-icons-bonsai-10281-lego-5702016914177",
    "price": 34.9,
    "title": "Lego bonsai 10281 (via retrait drive)",
    "imgUrl": "https://static-pepper.dealabs.com/threads/raw/LakmU/2960454_1/re/300x300/qt/60/2960454_1.jpg",
    "legoID": "10281",
    "retail": 49.99,
    "commentCount": 6,
    "temperature": 438.32,
    "published": 1735090097,
    "linkDealLabs": "https://www.dealabs.com/share-deal/2960454"
  },
  {
    "discount": 18.5,
    "link": "https://misterbricks.nl/lego-technic-42207-ferrari-sf-24-f1-auto.html",
    "price": 187.44,
    "title": "[Précommande] LEGO Technic (42207) - F1 Ferrari SF-24 (misterbricks.nl)",
    "imgUrl": "https://static-pepper.dealabs.com/threads/raw/Ij3Ri/2960166_1/re/300x300/qt/60/2960166_1.jpg",
    "legoID": "42207",
    "retail": 229.99,
    "commentCount": 19,
    "temperature": 758.65,
    "published": 1735043979,
    "linkDealLabs": "https://www.dealabs.com/share-deal/2960166"
  },
  {
    "discount": 30,
    "link": "https://www.king-jouet.com/jeu-jouet/jeux-constructions/lego-planchettes/ref-918728-10303-lego-icons-le-grand-huit.htm",
    "price": 279.99,
    "title": "Lego Icons (10303) - Le Grand Huit (Sélection de Magasins)",
    "imgUrl": "https://static-pepper.dealabs.com/threads/raw/WM425/2960150_1/re/300x300/qt/60/2960150_1.jpg",
    "legoID": "10303",
    "retail": 399.99,
    "commentCount": 34,
    "temperature": 364.96,
    "published": 1735042075,
    "linkDealLabs": "https://www.dealabs.com/share-deal/2960150"
  },
  {
    "discount": 32.09,
    "link": "https://www.amazon.fr/dp/B0CFVY9DZD?psc=1",
    "price": 7.49,
    "title": "LEGO DREAMZzz 71472 : la Montgolfière Narval d'Izzie.",
    "imgUrl": "https://static-pepper.dealabs.com/threads/raw/K23UR/2959883_1/re/300x300/qt/60/2959883_1.jpg",
    "legoID": "71472",
    "retail": 11.03,
    "commentCount": 0,
    "temperature": 47.08,
    "published": 1734994700,
    "linkDealLabs": "https://www.dealabs.com/share-deal/2959883"
  },
  {
    "discount": 30,
    "link": "https://www.king-jouet.com/jeu-jouet/jeux-constructions/lego-planchettes/ref-918810-75350-lego-star-wars-le-casque-du-commandant-clone-cody.htm",
    "price": 48.99,
    "title": "LEGO Star Wars 75350 - Le Casque du Commandant Clone Cody (via retrait magasins)",
    "imgUrl": "https://static-pepper.dealabs.com/threads/raw/PRdSH/2959625_1/re/300x300/qt/60/2959625_1.jpg",
    "legoID": "75350",
    "retail": 69.99,
    "commentCount": 16,
    "temperature": 72.08,
    "published": 1734966253,
    "linkDealLabs": "https://www.dealabs.com/share-deal/2959625"
  },
  {
    "discount": 50.01,
    "link": "https://www.lagranderecre.fr/-50-sur-une-selection-de-lego-dreamzzz.html",
    "price": 34.99,
    "title": "50% de réduction sur une sélection de Lego dreamzzz (ex : La tour du marchand de sable Lego Dreamzzz 71477)",
    "imgUrl": "https://static-pepper.dealabs.com/threads/raw/ksDWp/2959566_1/re/300x300/qt/60/2959566_1.jpg",
    "legoID": "71477",
    "retail": 69.99,
    "commentCount": 12,
    "temperature": 319.47,
    "published": 1734962219,
    "linkDealLabs": "https://www.dealabs.com/share-deal/2959566"
  },
  {
    "discount": 11.37,
    "link": "https://www.amazon.fr/dp/B0BBRYHTPS?smid=A1X6FK5RDHNB96",
    "price": 7.95,
    "title": "LEGO 31134 Creator 3-en-1 La Navette Spatiale",
    "imgUrl": "https://static-pepper.dealabs.com/threads/raw/lMuSv/2959455_1/re/300x300/qt/60/2959455_1.jpg",
    "legoID": "31134",
    "retail": 8.97,
    "commentCount": 0,
    "temperature": 75.27,
    "published": 1734950120,
    "linkDealLabs": "https://www.dealabs.com/share-deal/2959455"
  },
  {
    "discount": 20.56,
    "link": "https://www.amazon.fr/dp/B0CFVYPKGB?smid=A1X6FK5RDHNB96",
    "price": 13.99,
    "title": "Jeu de construction Lego Creator 3-en-1 Le Camion Remorque avec Hélicoptère (31146)",
    "imgUrl": "https://static-pepper.dealabs.com/threads/raw/VlNmO/2959416_1/re/300x300/qt/60/2959416_1.jpg",
    "legoID": "31146",
    "retail": 17.61,
    "commentCount": 1,
    "temperature": 62.58,
    "published": 1734946982,
    "linkDealLabs": "https://www.dealabs.com/share-deal/2959416"
  },
  {
    "discount": 28.17,
    "link": "https://www.amazon.fr/dp/B0CFVYKCBY?smid=A1X6FK5RDHNB96",
    "price": 44.53,
    "title": "LEGO DREAMZzz 2-en-1 La Tour du Marchand de Sable 71477",
    "imgUrl": "https://static-pepper.dealabs.com/threads/raw/aBU0L/2959332_1/re/300x300/qt/60/2959332_1.jpg",
    "legoID": "71477",
    "retail": 61.99,
    "commentCount": 1,
    "temperature": 45.66,
    "published": 1734938227,
    "linkDealLabs": "https://www.dealabs.com/share-deal/2959332"
  },
  {
    "discount": 33.24,
    "link": "https://www.amazon.fr/dp/B0CFVYMSQF?smid=A1X6FK5RDHNB96",
    "price": 5,
    "title": "LEGO DREAMZzz 71471 La Voiture Tout-Terrain de Mateo",
    "imgUrl": "https://static-pepper.dealabs.com/threads/raw/jzt5b/2959312_1/re/300x300/qt/60/2959312_1.jpg",
    "legoID": "71471",
    "retail": 7.49,
    "commentCount": 0,
    "temperature": 67.82,
    "published": 1734932760,
    "linkDealLabs": "https://www.dealabs.com/share-deal/2959312"
  },
  {
    "discount": 0,
    "link": "https://www.cdiscount.com/juniors/maquette-modelisme/lego-technic-42202-la-moto-ducati-panigale-v4-s/f-12084-lego42202.html",
    "price": 159.99,
    "title": "[Précommande] Lego Technic 42202 Moto Ducati Panigale",
    "imgUrl": "https://static-pepper.dealabs.com/threads/raw/btJ15/2958711_1/re/300x300/qt/60/2958711_1.jpg",
    "legoID": "42202",
    "retail": 0,
    "commentCount": 10,
    "temperature": 68.8,
    "published": 1734849921,
    "linkDealLabs": "https://www.dealabs.com/share-deal/2958711"
  },
  {
    "discount": 16.23,
    "link": "https://www.action.com/fr-fr/p/3211973/lego-creator-la-licorne-magique/",
    "price": 7.95,
    "title": "Jeu de construction Lego Creator (31140) - La licorne magique où navette spatiale",
    "imgUrl": "https://static-pepper.dealabs.com/threads/raw/QdJ54/2958572_1/re/300x300/qt/60/2958572_1.jpg",
    "legoID": "31140",
    "retail": 9.49,
    "commentCount": 5,
    "temperature": 94.8,
    "published": 1734814717,
    "linkDealLabs": "https://www.dealabs.com/share-deal/2958572"
  },
  {
    "discount": 8.44,
    "link": "https://www.amazon.fr/dp/B09BNX79CM?psc=1",
    "price": 13.99,
    "title": "Jeu de Construction LEGO Minecraft 21178 : Le Refuge du Renard",
    "imgUrl": "https://static-pepper.dealabs.com/threads/raw/kKaLA/2958180_1/re/300x300/qt/60/2958180_1.jpg",
    "legoID": "21178",
    "retail": 15.28,
    "commentCount": 1,
    "temperature": 18.56,
    "published": 1734776915,
    "linkDealLabs": "https://www.dealabs.com/share-deal/2958180"
  },
  {
    "discount": 0,
    "link": "https://www.cdiscount.com/juniors/maquette-modelisme/lego-harry-potter-76453-le-manoir-des-malefoy-je/f-12084-lego76453.html",
    "price": 119.99,
    "title": "[Précommande] Jouet Lego Harry Potter 76453 Le Manoir des Malefoy",
    "imgUrl": "https://static-pepper.dealabs.com/threads/raw/1L5sK/2957764_1/re/300x300/qt/60/2957764_1.jpg",
    "legoID": "76453",
    "retail": 0,
    "commentCount": 2,
    "temperature": 41.43,
    "published": 1734718632,
    "linkDealLabs": "https://www.dealabs.com/share-deal/2957764"
  },
  {
    "discount": 19.52,
    "link": "",
    "price": 119.92,
    "title": "LEGO Technic Mercedes-AMG F1 W14 E Performance 42171 LEGO 77 - Carre senart (77)",
    "imgUrl": "https://static-pepper.dealabs.com/threads/raw/xpNBt/2957652_1/re/300x300/qt/60/2957652_1.jpg",
    "legoID": "42171",
    "retail": 149,
    "commentCount": 0,
    "temperature": 69.97,
    "published": 1734710967,
    "linkDealLabs": "https://www.dealabs.com/share-deal/2957652"
  },
  {
    "discount": 18.23,
    "link": "https://www.fnac.com/LEGO-Friends-41728-Le-snack-du-centre-ville/a17484009/w-4",
    "price": 17.99,
    "title": "Jouet Lego Friends le snack du centre-ville 41728 (Sélection de villes)",
    "imgUrl": "https://static-pepper.dealabs.com/threads/raw/jlsQ0/2957588_1/re/300x300/qt/60/2957588_1.jpg",
    "legoID": "41728",
    "retail": 22,
    "commentCount": 0,
    "temperature": -11.29,
    "published": 1734705752,
    "linkDealLabs": "https://www.dealabs.com/share-deal/2957588"
  },
  {
    "discount": 31.09,
    "link": "https://www.alternate.fr/Lego/Icons-La-couronne-Jouets-de-construction/html/product/100044321",
    "price": 68.9,
    "title": "LEGO Icons - La Couronne de Noël (10340)",
    "imgUrl": "https://static-pepper.dealabs.com/threads/raw/5mSD6/2957045_1/re/300x300/qt/60/2957045_1.jpg",
    "legoID": "10340",
    "retail": 99.99,
    "commentCount": 3,
    "temperature": 175.69,
    "published": 1734643198,
    "linkDealLabs": "https://www.dealabs.com/share-deal/2957045"
  },
  {
    "discount": 14.88,
    "link": "https://www.amazon.fr/dp/B09BPGNHP4",
    "price": 21.28,
    "title": "Jouet Lego 76213 Marvel La Salle du Trône du Roi Namor",
    "imgUrl": "https://static-pepper.dealabs.com/threads/raw/0hWrM/2956756_1/re/300x300/qt/60/2956756_1.jpg",
    "legoID": "76213",
    "retail": 25,
    "commentCount": 0,
    "temperature": -9.61,
    "published": 1734621401,
    "linkDealLabs": "https://www.dealabs.com/share-deal/2956756"
  },
  {
    "discount": 15.9,
    "link": "https://www.alternate.fr/Lego/41838-Jouets-de-construction/html/product/100044260",
    "price": 89.9,
    "title": "Lego 41838 Souvenir de Voyage",
    "imgUrl": "https://static-pepper.dealabs.com/threads/raw/DRLrm/2956701_1/re/300x300/qt/60/2956701_1.jpg",
    "legoID": "41838",
    "retail": 106.9,
    "commentCount": 1,
    "temperature": 28.23,
    "published": 1734617688,
    "linkDealLabs": "https://www.dealabs.com/share-deal/2956701"
  },
  {
    "discount": 0,
    "link": "https://www.king-jouet.com/jeu-jouet/jeux-constructions/lego-planchettes/ref-951597-76429-lego-harry-potter-le-choixpeau-magique-qui-parle.htm",
    "price": 89.99,
    "title": "LEGO 76429 Harry Potter - Le Choixpeau Magique qui Parle",
    "imgUrl": "https://static-pepper.dealabs.com/threads/raw/ioAkR/2956572_1/re/300x300/qt/60/2956572_1.jpg",
    "legoID": "76429",
    "retail": 0,
    "commentCount": 1,
    "temperature": -93.16,
    "published": 1734608055,
    "linkDealLabs": "https://www.dealabs.com/share-deal/2956572"
  },
  {
    "discount": 30.01,
    "link": "https://www.king-jouet.com/jeu-jouet/jeux-constructions/lego-planchettes/ref-967914-10370-lego-botanique-etoile-noel.htm",
    "price": 34.99,
    "title": "Jeu de construction Lego (10370) - L’étoile de Noël",
    "imgUrl": "https://static-pepper.dealabs.com/threads/raw/HQO2C/2956538_1/re/300x300/qt/60/2956538_1.jpg",
    "legoID": "10370",
    "retail": 49.99,
    "commentCount": 37,
    "temperature": 1226.45,
    "published": 1734605578,
    "linkDealLabs": "https://www.dealabs.com/share-deal/2956538"
  },
  {
    "discount": 35.66,
    "link": "https://www.fnac.com/LEGO-Star-Wars-75364-L-E-wing-de-la-Nouvelle-Republique-contre-le-chasseur-de-Shin-Hati/a17918379/w-4",
    "price": 62.99,
    "title": "Lego Star Wars 75364 L’E-wing de la Nouvelle République contre le chasseur de Shin Hati (Sélection de magasins)",
    "imgUrl": "https://static-pepper.dealabs.com/threads/raw/uSH98/2956312_1/re/300x300/qt/60/2956312_1.jpg",
    "legoID": "75364",
    "retail": 97.9,
    "commentCount": 4,
    "temperature": 40.15,
    "published": 1734594147,
    "linkDealLabs": "https://www.dealabs.com/share-deal/2956312"
  },
  {
    "discount": 9.09,
    "link": "https://www.amazon.fr/dp/B0CWH3FMKS?smid=A1X6FK5RDHNB96",
    "price": 99.99,
    "title": "LEGO Star Wars - C-3PO (75398)",
    "imgUrl": "https://static-pepper.dealabs.com/threads/raw/6eQBT/2956096_1/re/300x300/qt/60/2956096_1.jpg",
    "legoID": "75398",
    "retail": 109.99,
    "commentCount": 6,
    "temperature": 12.58,
    "published": 1734551530,
    "linkDealLabs": "https://www.dealabs.com/share-deal/2956096"
  },
  {
    "discount": 19.62,
    "link": "https://www.amazon.fr/dp/B0CFVYRZ27?smid=A1X6FK5RDHNB96",
    "price": 19.99,
    "title": "LEGO City - La voiture de course et le camion de transport de voitures (60406)",
    "imgUrl": "https://static-pepper.dealabs.com/threads/raw/yperb/2956031_1/re/300x300/qt/60/2956031_1.jpg",
    "legoID": "60406",
    "retail": 24.87,
    "commentCount": 0,
    "temperature": 42.82,
    "published": 1734546538,
    "linkDealLabs": "https://www.dealabs.com/share-deal/2956031"
  },
  {
    "discount": 16.71,
    "link": "https://www.carrefour.fr/p/lego-dreamzzz-les-creatures-de-la-sorciere-des-cauchemars-71483-lego-5702017584287",
    "price": 29.9,
    "title": "Jouet Lego DREAMZzz Les Créatures de la Sorcière des Cauchemars 71483",
    "imgUrl": "https://static-pepper.dealabs.com/threads/raw/XSNJ4/2955072_1/re/300x300/qt/60/2955072_1.jpg",
    "legoID": "71483",
    "retail": 35.9,
    "commentCount": 0,
    "temperature": 23.21,
    "published": 1734463229,
    "linkDealLabs": "https://www.dealabs.com/share-deal/2955072"
  },
  {
    "discount": 5.56,
    "link": "https://www.carrefour.fr/p/lego-creator-le-perroquet-exotique-rose-31144-lego-5702017468648",
    "price": 16.99,
    "title": "LEGO Creator 31144 - Le Perroquet Exotique Rose",
    "imgUrl": "https://static-pepper.dealabs.com/threads/raw/iRobA/2954985_1/re/300x300/qt/60/2954985_1.jpg",
    "legoID": "31144",
    "retail": 17.99,
    "commentCount": 5,
    "temperature": 73.01,
    "published": 1734457340,
    "linkDealLabs": "https://www.dealabs.com/share-deal/2954985"
  },
  {
    "discount": 11.29,
    "link": "https://www.amazon.fr/dp/B0BBRZYFB9?smid=A1X6FK5RDHNB96",
    "price": 6.99,
    "title": "Jouet Lego Ninjago 71780 : La Voiture de Course Ninja de Kai",
    "imgUrl": "https://static-pepper.dealabs.com/threads/raw/ns3n5/2954369_1/re/300x300/qt/60/2954369_1.jpg",
    "legoID": "71780",
    "retail": 7.88,
    "commentCount": 2,
    "temperature": 49.28,
    "published": 1734414217,
    "linkDealLabs": "https://www.dealabs.com/share-deal/2954369"
  },
  {
    "discount": 33.36,
    "link": "https://www.carrefour.fr/p/lego-creator-les-fleurs-de-cerisier-40725-lego-5702017596976",
    "price": 9.99,
    "title": "Sélection de sets LEGO icons à 9.99€ en magasin - Ex : Lego (40725) Les Fleurs de Cerisier (Sélection de magasins)",
    "imgUrl": "https://static-pepper.dealabs.com/threads/raw/MjZ2q/2954284_1/re/300x300/qt/60/2954284_1.jpg",
    "legoID": "40725",
    "retail": 14.99,
    "commentCount": 4,
    "temperature": 575.84,
    "published": 1734391108,
    "linkDealLabs": "https://www.dealabs.com/share-deal/2954284"
  },
  {
    "discount": 34.19,
    "link": "https://www.carrefour.fr/p/lego-icons-l-orchidee-10311-lego-5702017224336",
    "price": 32.9,
    "title": "LEGO Icons (10311) - L'orchidée (Sélection de Magasins, Ex : Drancy 93)",
    "imgUrl": "https://static-pepper.dealabs.com/threads/raw/MuDWW/2954213_1/re/300x300/qt/60/2954213_1.jpg",
    "legoID": "10311",
    "retail": 49.99,
    "commentCount": 12,
    "temperature": 679.95,
    "published": 1734385806,
    "linkDealLabs": "https://www.dealabs.com/share-deal/2954213"
  },
  {
    "discount": 31.1,
    "link": "https://www.carrefour.fr/p/lego-minecraft-l-etabli-21265-lego-5702017583419",
    "price": 62,
    "title": "Jouet Lego Minecraft L’établi 21265 (Sélection de villes)",
    "imgUrl": "https://static-pepper.dealabs.com/threads/raw/4z94Z/2954059_1/re/300x300/qt/60/2954059_1.jpg",
    "legoID": "21265",
    "retail": 89.99,
    "commentCount": 7,
    "temperature": 260.85,
    "published": 1734377384,
    "linkDealLabs": "https://www.dealabs.com/share-deal/2954059"
  },
  {
    "discount": 20,
    "link": "https://www.cdiscount.com/juniors/maquette-modelisme/lego-star-wars-the-mandalorian-75403-grogu-et-so/f-12084-lego75403.html",
    "price": 79.99,
    "title": "[PRECOMMANDE] LEGO Star Wars : The Mandalorian 75403 Grogu et son landau",
    "imgUrl": "https://static-pepper.dealabs.com/threads/raw/6LRSm/2953971_1/re/300x300/qt/60/2953971_1.jpg",
    "legoID": "75403",
    "retail": 99.99,
    "commentCount": 5,
    "temperature": 85.59,
    "published": 1734372624,
    "linkDealLabs": "https://www.dealabs.com/share-deal/2953971"
  },
  {
    "discount": 25.41,
    "link": "https://www.kitstore.fr/p/lego-r-star-warstm-75387-embarquement-a-bord-du-tantive-ivtm",
    "price": 39.78,
    "title": "LEGO Star Wars 75387 - Embarquement à bord du Tantive IV",
    "imgUrl": "https://static-pepper.dealabs.com/threads/raw/rQjqJ/2953962_1/re/300x300/qt/60/2953962_1.jpg",
    "legoID": "75387",
    "retail": 53.33,
    "commentCount": 2,
    "temperature": 39.41,
    "published": 1734372068,
    "linkDealLabs": "https://www.dealabs.com/share-deal/2953962"
  },
  {
    "discount": 18.75,
    "link": "https://www.cdiscount.com/juniors/maquette-modelisme/lego-art-31214-love-set-de-construction-pour-adu/f-12084-lego31214.html",
    "price": 64.99,
    "title": "[Précommande] LEGO Art 31214 - LOVE",
    "imgUrl": "https://static-pepper.dealabs.com/threads/raw/CRLmg/2953954_1/re/300x300/qt/60/2953954_1.jpg",
    "legoID": "31214",
    "retail": 79.99,
    "commentCount": 4,
    "temperature": 39.04,
    "published": 1734372025,
    "linkDealLabs": "https://www.dealabs.com/share-deal/2953954"
  },
  {
    "discount": 24.03,
    "link": "https://www.kitstore.fr/p/lego-r-star-warstm-75375-millennium-falcontm",
    "price": 60.49,
    "title": "LEGO Star Wars 75375 - Millennium Falcon",
    "imgUrl": "https://static-pepper.dealabs.com/threads/raw/3z6ej/2953960_1/re/300x300/qt/60/2953960_1.jpg",
    "legoID": "75375",
    "retail": 79.62,
    "commentCount": 0,
    "temperature": -86.94,
    "published": 1734371997,
    "linkDealLabs": "https://www.dealabs.com/share-deal/2953960"
  },
  {
    "discount": 24.13,
    "link": "https://www.kitstore.fr/p/lego-r-harry-pottertm-76439-ollivander-et-madame-guipure-pret-a-porter-pour-mages-et-sorciers",
    "price": 64.87,
    "title": "LEGO Harry Potter 76439 Ollivander et Madame Guipure, prêt-à-porter pour mages et sorciers",
    "imgUrl": "https://static-pepper.dealabs.com/threads/raw/QoXeA/2953936_1/re/300x300/qt/60/2953936_1.jpg",
    "legoID": "76439",
    "retail": 85.5,
    "commentCount": 2,
    "temperature": 15.44,
    "published": 1734371141,
    "linkDealLabs": "https://www.dealabs.com/share-deal/2953936"
  },
  {
    "discount": 21.49,
    "link": "https://www.amazon.fr/dp/B01MRT58RZ?smid=A1X6FK5RDHNB96",
    "price": 47.1,
    "title": "Jeu de construction Lego Icons Botanical Collection Le Bouquet de Roses - 10328",
    "imgUrl": "https://static-pepper.dealabs.com/threads/raw/ENk0d/2953884_1/re/300x300/qt/60/2953884_1.jpg",
    "legoID": "10328",
    "retail": 59.99,
    "commentCount": 3,
    "temperature": -38.05,
    "published": 1734368346,
    "linkDealLabs": "https://www.dealabs.com/share-deal/2953884"
  },
  {
    "discount": 17.65,
    "link": "https://www.cdiscount.com/juniors/maquette-modelisme/lego-ideas-21333-vincent-van-gogh-la-nuit-etoile/f-12084-lego21333.html",
    "price": 139.99,
    "title": "Jeu de construction Lego Ideas Vincent Van Gogh La Nuit Étoilée - 21333",
    "imgUrl": "https://static-pepper.dealabs.com/threads/raw/zaV3B/2953703_1/re/300x300/qt/60/2953703_1.jpg",
    "legoID": "21333",
    "retail": 169.99,
    "commentCount": 7,
    "temperature": 47.93,
    "published": 1734356560,
    "linkDealLabs": "https://www.dealabs.com/share-deal/2953703"
  },
  {
    "discount": 4.27,
    "link": "https://www.amazon.fr/dp/B0CFVZ1LCY?smid=A1X6FK5RDHNB96",
    "price": 21.99,
    "title": "Lego 76921 Speed Champion Audi S1 e-Tron Quattro",
    "imgUrl": "https://static-pepper.dealabs.com/threads/raw/0ML0l/2953448_1/re/300x300/qt/60/2953448_1.jpg",
    "legoID": "76921",
    "retail": 22.97,
    "commentCount": 0,
    "temperature": -56.41,
    "published": 1734338325,
    "linkDealLabs": "https://www.dealabs.com/share-deal/2953448"
  },
  {
    "discount": 20,
    "link": "https://www.amazon.fr/dp/B09BNV2Q49?smid=A1X6FK5RDHNB96",
    "price": 39.99,
    "title": "Lego Icons 10311 - L'Orchidée",
    "imgUrl": "https://static-pepper.dealabs.com/threads/raw/GKC1L/2952003_1/re/300x300/qt/60/2952003_1.jpg",
    "legoID": "10311",
    "retail": 49.99,
    "commentCount": 7,
    "temperature": 53.99,
    "published": 1734187626,
    "linkDealLabs": "https://www.dealabs.com/share-deal/2952003"
  },
  {
    "discount": 33.58,
    "link": "https://www.cdiscount.com/juniors/maquette-modelisme/lego-r-10875-duplo-le-train-de-marchandises-avec/f-12084-leg10875.html",
    "price": 79.71,
    "title": "Jouet Lego Duplo 10875 - Le Train De Marchandises avec Son et Lumière",
    "imgUrl": "https://static-pepper.dealabs.com/threads/raw/RO9SZ/2951444_1/re/300x300/qt/60/2951444_1.jpg",
    "legoID": "10875",
    "retail": 120,
    "commentCount": 4,
    "temperature": 44.46,
    "published": 1734124031,
    "linkDealLabs": "https://www.dealabs.com/share-deal/2951444"
  },
  {
    "discount": 37.05,
    "link": "https://www.smythstoys.com/fr/fr-fr/jouets/lego/lego-speed-champions/lego-speed-champions-76919-formule-1-mclaren/p/232269",
    "price": 16.99,
    "title": "Lego Speed Champions 76919 Formule 1 McLaren",
    "imgUrl": "https://static-pepper.dealabs.com/threads/raw/0VXhv/2951249_1/re/300x300/qt/60/2951249_1.jpg",
    "legoID": "76919",
    "retail": 26.99,
    "commentCount": 12,
    "temperature": 779.17,
    "published": 1734112219,
    "linkDealLabs": "https://www.dealabs.com/share-deal/2951249"
  },
  {
    "discount": 0,
    "link": "https://www.auchan.fr/lego-marvel-76281-le-x-jet-des-x-men-jouet-d-avion-chasseur-avec-minifigurines-de-super-heros-wolverine/pr-C1775619?offerType=DEFAULT",
    "price": 48.99,
    "title": "Jeu de construction Lego Marvel 76281 Le X-Jet des X-Men (via 21€ sur la carte fidélité)",
    "imgUrl": "https://static-pepper.dealabs.com/threads/raw/koTGF/2951034_1/re/300x300/qt/60/2951034_1.jpg",
    "legoID": "76281",
    "retail": 0,
    "commentCount": 0,
    "temperature": 52.73,
    "published": 1734099980,
    "linkDealLabs": "https://www.dealabs.com/share-deal/2951034"
  },
  {
    "discount": 20.01,
    "link": "https://www.carrefour.fr/p/lego-iconic-tournesols-40524-lego-5702017165646",
    "price": 11.99,
    "title": "LEGO Iconic 40524 Tournesols",
    "imgUrl": "https://static-pepper.dealabs.com/threads/raw/CAVus/2950860_1/re/300x300/qt/60/2950860_1.jpg",
    "legoID": "40524",
    "retail": 14.99,
    "commentCount": 2,
    "temperature": 202.8,
    "published": 1734090811,
    "linkDealLabs": "https://www.dealabs.com/share-deal/2950860"
  },
  {
    "discount": 31.55,
    "link": "https://www.carrefour.fr/p/lego-technic-mercedes-amg-f1-w14-e-performance-42171-lego-5702017583563",
    "price": 149.9,
    "title": "LEGO Technic Mercedes-AMG F1 W14 E Performance 42171 LEGO",
    "imgUrl": "https://static-pepper.dealabs.com/threads/raw/wvAm0/2950807_1/re/300x300/qt/60/2950807_1.jpg",
    "legoID": "42171",
    "retail": 219,
    "commentCount": 17,
    "temperature": 621.9,
    "published": 1734087562,
    "linkDealLabs": "https://www.dealabs.com/share-deal/2950807"
  },
  {
    "discount": 20.01,
    "link": "https://www.carrefour.fr/p/lego-star-wars-le-temple-jedi-de-tenoo-75358-lego-5702017421391",
    "price": 27.99,
    "title": "Lego Star Wars 75358 Le Temple Jedi de Tenoo",
    "imgUrl": "https://static-pepper.dealabs.com/threads/raw/ymcVd/2950805_1/re/300x300/qt/60/2950805_1.jpg",
    "legoID": "75358",
    "retail": 34.99,
    "commentCount": 0,
    "temperature": 9.17,
    "published": 1734087522,
    "linkDealLabs": "https://www.dealabs.com/share-deal/2950805"
  },
  {
    "discount": 27.31,
    "link": "https://www.alternate.fr/Lego/Technic-Mercedes-AMG-F1-W14-E-Performance-Jouets-de-construction/html/product/100012662",
    "price": 159.9,
    "title": "Jeu de construction Lego Technic Mercedes-AMG F1 W14 E Performance (42171) 1642 pièces",
    "imgUrl": "https://static-pepper.dealabs.com/threads/raw/oC1Il/2950613_1/re/300x300/qt/60/2950613_1.jpg",
    "legoID": "42171",
    "retail": 219.99,
    "commentCount": 17,
    "temperature": 295.7,
    "published": 1734079931,
    "linkDealLabs": "https://www.dealabs.com/share-deal/2950613"
  },
  {
    "discount": 9.26,
    "link": "https://www.amazon.fr/dp/B00C1DIRXQ?smid=A1X6FK5RDHNB96",
    "price": 229.99,
    "title": "Lego Icons (10341) - Le système de lancement spatial d'Artemis de la NASA",
    "imgUrl": "https://static-pepper.dealabs.com/threads/raw/xdZLb/2949720_1/re/300x300/qt/60/2949720_1.jpg",
    "legoID": "10341",
    "retail": 253.45,
    "commentCount": 10,
    "temperature": -45.35,
    "published": 1734003254,
    "linkDealLabs": "https://www.dealabs.com/share-deal/2949720"
  },
  {
    "discount": 0,
    "link": "https://www.amazon.fr/dp/B0CWH3FX31?smid=A1X6FK5RDHNB96",
    "price": 139.99,
    "title": "LEGO Star Wars 75389 - Le Faucon Noir, Set de Vaisseau Spatial à Collectionner",
    "imgUrl": "https://static-pepper.dealabs.com/threads/raw/lS39Q/2949475_1/re/300x300/qt/60/2949475_1.jpg",
    "legoID": "75389",
    "retail": 0,
    "commentCount": 0,
    "temperature": -89.85,
    "published": 1733985444,
    "linkDealLabs": "https://www.dealabs.com/share-deal/2949475"
  },
  {
    "discount": 50.19,
    "link": "",
    "price": 13.27,
    "title": "Calendrier de l'avent Lego Star Wars 75395 et Marvel 76293 - Trignac (44)",
    "imgUrl": "https://static-pepper.dealabs.com/threads/raw/QdqpX/2948980_1/re/300x300/qt/60/2948980_1.jpg",
    "legoID": "75395",
    "retail": 26.64,
    "commentCount": 12,
    "temperature": 328.31,
    "published": 1733924106,
    "linkDealLabs": "https://www.dealabs.com/share-deal/2948980"
  },
  {
    "discount": 24.44,
    "link": "",
    "price": 339.99,
    "title": "Lego 42172 - Maclaren p1 - Villeneuve d'Ascq (59)",
    "imgUrl": "https://static-pepper.dealabs.com/threads/raw/DFSYu/2948822_1/re/300x300/qt/60/2948822_1.jpg",
    "legoID": "42172",
    "retail": 449.99,
    "commentCount": 1,
    "temperature": -45.29,
    "published": 1733912750,
    "linkDealLabs": "https://www.dealabs.com/share-deal/2948822"
  }
]